{"Key":{"ScheduledDayCode":2023010,"ScheduledPlanName":"04","Item1":2023010,"Item2":"04"},"ScheduledDayCode":2023010,"Id":"4420","Name":"04","LineId":655,"TrainTypeId":0,"StartSite":{"ElementId":"E_PT10_PT5_VEC","Offset":11000,"AdditionalPos":716500,"AdditionalName":"P2C_VEC"},"EndSite":{"ElementId":"E_PT2_PT1_CAR","Offset":71000,"AdditionalPos":12223500,"AdditionalName":"P2C_CAR"},"StartTime":{"DateTime":"2023-01-10T04:32:47"},"EndTime":{"DateTime":"2023-01-10T04:35:37"},"Trips":{"1":{"ScheduledDayCode":2023010,"ScheduledPlanId":"4420","ScheduledPlanName":"04","Id":4421,"Name":"P2C_VEC - P2C_CAR","TripNumber":1,"TripCode":"","StartPos":{"ElementId":"E_PT10_PT5_VEC","Offset":11000,"AdditionalPos":716500,"AdditionalName":"P2C_VEC"},"EndPos":{"ElementId":"E_PT2_PT1_CAR","Offset":71000,"AdditionalPos":12223500,"AdditionalName":"P2C_CAR"},"StartTime":{"DateTime":"2023-01-10T04:32:47"},"EndTime":{"DateTime":"2023-01-10T04:35:37"},"TimedLocations":[{"Description":"P2C_VEC","Pos":{"ElementId":"E_PT10_PT5_VEC","Offset":11000,"AdditionalPos":716500,"AdditionalName":"P2C_VEC"},"Arrival":{"DateTime":"2023-01-10T04:32:47"},"Departure":{"DateTime":"2023-01-10T04:33:12"},"HasStopping":true},{"Description":"P2C_CAR","Pos":{"ElementId":"E_PT2_PT1_CAR","Offset":71000,"AdditionalPos":12223500,"AdditionalName":"P2C_CAR"},"Arrival":{"DateTime":"2023-01-10T04:35:12"},"Departure":{"DateTime":"2023-01-10T04:35:37"},"HasStopping":true}],"DelaySeconds":0,"TrainLength":0}},"IsSparePlan":false}